sdx_dl/DrissionPage.pyi
sdx_dl/__init__.py
sdx_dl/cli.py
sdx_dl/py.typed
sdx_dl/sdxclasses.py
sdx_dl/sdxconsole.py
sdx_dl/sdximdb.py
sdx_dl/sdxlib.py
sdx_dl/sdxlocale.py
sdx_dl/sdxlogger.py
sdx_dl/sdxparser.py
sdx_dl/sdxsubxapi.py
sdx_dl/sdxutils.py
sdx_dl/cf_bypasser/CloudflareBypasser.py
sdx_dl/cf_bypasser/__init__.py
sdx_dl/cf_bypasser/get_cf_bypass.py
sdx_dl/cf_bypasser/cache/__init__.py
sdx_dl/cf_bypasser/cache/cookie_cache.py
sdx_dl/cf_bypasser/utils/__init__.py
sdx_dl/cf_bypasser/utils/config.py
sdx_dl/cf_bypasser/utils/misc.py
sdx_dl/language/__init__.py
sdx_dl/language/en.json
sdx_dl/language/es.json
subdx_dl-2.0.7.dist-info/licenses/LICENSE
subdx_dl-2.0.7.dist-info/METADATA
subdx_dl-2.0.7.dist-info/WHEEL
subdx_dl-2.0.7.dist-info/entry_points.txt
subdx_dl-2.0.7.dist-info/top_level.txt
subdx_dl-2.0.7.dist-info/RECORD
