Metadata-Version: 2.4
Name: subdx-dl
Version: 2.0.7
Summary: A command line tool to download the best matching subtitle from subdivx.com
Author-email: Spheres-cu <sasuke.pc@gmail.com>
Maintainer-email: "C. S. M." <sasuke.pc@gmail.com>
License-Expression: GPL-3.0-or-later AND BSD-3-Clause-Modification
Project-URL: Homepage, https://github.com/Spheres-cu/subdx-dl
Project-URL: Issues, https://github.com/Spheres-cu/subdx-dl/issues
Project-URL: Examples, https://github.com/Spheres-cu/subdx-dl#examples
Keywords: cli-tool,subdivx,subdivx-downloader,subtitles
Classifier: Programming Language :: Python :: 3.10
Classifier: Development Status :: 5 - Production/Stable
Classifier: Environment :: Console
Classifier: Operating System :: OS Independent
Requires-Python: >=3.10
License-File: LICENSE
Requires-Dist: beautifulsoup4>=4.14.3
Requires-Dist: html5lib>=1.1
Requires-Dist: guessit>=3.8.0
Requires-Dist: rarfile>=4.2
Requires-Dist: urllib3[brotli]>=2.6.1
Requires-Dist: certifi>=2025.11.12
Requires-Dist: rich>=14.2.0
Requires-Dist: readchar>=4.2.1
Requires-Dist: html2text>=2025.4.15
Requires-Dist: lxml>=5.4.0
Requires-Dist: lxml_html_clean>=0.4.2
Requires-Dist: DrissionPage==4.1.1.2
Requires-Dist: pyquery==2.0.1
Requires-Dist: parse==1.20.2
Requires-Dist: w3lib>=2.3.1
Requires-Dist: requests<3,>=2.32.3
Requires-Dist: importlib-metadata; python_version < "3.10"
Dynamic: license-file
